dogebuild_hello/hello.py
dogebuild_hello/loader.py
dogebuild_hello/__init__.py
dogebuild_hello-0.1.0.dev1.dist-info/DESCRIPTION.rst
dogebuild_hello-0.1.0.dev1.dist-info/METADATA
dogebuild_hello-0.1.0.dev1.dist-info/metadata.json
dogebuild_hello-0.1.0.dev1.dist-info/RECORD
dogebuild_hello-0.1.0.dev1.dist-info/top_level.txt
dogebuild_hello-0.1.0.dev1.dist-info/WHEEL
