Metadata-Version: 2.0
Name: dogebuild-hello
Version: 0.1.0.dev1
Summary: A hello world plugin for dogebuild.
Home-page: https://github.com/dogebuild/dogebuild-hello
Author: Kirill Sulim
Author-email: kirillsulim@gmail.com
License: MIT
Keywords: dogebuild builder helloworld
Platform: UNKNOWN
Classifier: Development Status :: 2 - Pre-Alpha
Classifier: Intended Audience :: Developers
Classifier: License :: OSI Approved :: MIT License
Classifier: Natural Language :: English
Classifier: Operating System :: OS Independent
Classifier: Programming Language :: Python :: 3.3
Classifier: Programming Language :: Python :: 3.4
Classifier: Topic :: Software Development
